py3dephell/__init__.py
py3dephell/py3prov.py
py3dephell/py3req.py
py3dephell-0.4.1.dist-info/COPYING
py3dephell-0.4.1.dist-info/METADATA
py3dephell-0.4.1.dist-info/WHEEL
py3dephell-0.4.1.dist-info/entry_points.txt
py3dephell-0.4.1.dist-info/top_level.txt
py3dephell-0.4.1.dist-info/RECORD
