Metadata-Version: 2.2
Name: py3dephell
Version: 0.4.1
Summary: Helps to control project dependencies and provides
Author-email: Daniel Zagaynov <kotopesutility@altlinux.org>
License: GPLv2
Project-URL: Homepage, https://github.com/altlinux/py3dephell.git
Keywords: dependencies,provides,requirements,dependency hell
Classifier: Development Status :: 4 - Beta
Classifier: Environment :: Console
Classifier: License :: OSI Approved :: GNU General Public License v2 (GPLv2)
Classifier: Operating System :: Unix
Classifier: Programming Language :: Python :: 3
Classifier: Topic :: System :: Software Distribution
Requires-Python: >=3.10
License-File: COPYING
